drive_cli/__init__.py
drive_cli/actions.py
drive_cli/auth.py
drive_cli/dcli.py
drive_cli/oauth.json
drive_cli/utils.py
tests/__init__.py
tests/base.py
tests/test_auth.py
drive_cli-2.1.0.dist-info/LICENSE
drive_cli-2.1.0.dist-info/METADATA
drive_cli-2.1.0.dist-info/WHEEL
drive_cli-2.1.0.dist-info/entry_points.txt
drive_cli-2.1.0.dist-info/top_level.txt
drive_cli-2.1.0.dist-info/RECORD
