Metadata-Version: 2.1
Name: drive-cli
Version: 2.1.0
Summary: CLI client for Google Drive
Home-page: https://github.com/nurdtechie98/drive-cli
Author: Chirag Shetty
Author-email: nurdtechie98@gmail.com
License: UNKNOWN
Platform: UNKNOWN
Classifier: Programming Language :: Python :: 3
Classifier: Development Status :: 3 - Alpha
Classifier: Intended Audience :: End Users/Desktop
Classifier: Natural Language :: English
Classifier: Topic :: Utilities
Classifier: License :: OSI Approved :: MIT License
Classifier: Operating System :: OS Independent
Requires-Dist: requests (==2.21.0)
Requires-Dist: click (==7.0)
Requires-Dist: colorama (==0.4.1)
Requires-Dist: pick (==0.6.4)
Requires-Dist: google-api-python-client (==1.7.8)
Requires-Dist: oauth2client (==4.1.3)
Requires-Dist: prettytable (==0.7.2)
Requires-Dist: httplib2 (==0.12.1)
Requires-Dist: pyfiglet (==0.8.post1)
Requires-Dist: windows-curses ; platform_system == "Windows"
